[
  {
    "id": "quiz1",
    "title": "JavaScript Basics QuizJavaScript Basics QuizJavaScript Basics Quiz",
    "date": "2024-09-10",
    "startTime": "2024-09-10T14:00:00Z",
    "endTime": "2024-09-10T15:00:00Z",
    "description": "A quiz to test your knowledge on basic JavaScript concepts.",
    "location": "Online",
    "batch": "10th"
  },
  {
    "id": "quiz2",
    "title": "Advanced C++ Programming",
    "date": "2024-09-15",
    "startTime": "2024-09-15T09:00:00Z",
    "endTime": "2024-09-15T10:30:00Z",
    "description": "Test your skills in advanced C++ programming techniques.",
    "location": "Room 204",
    "batch": "12th"
  },
  {
    "id": "quiz3",
    "title": "Machine Learning Fundamentals",
    "date": "2024-09-20",
    "startTime": "2024-09-20T11:00:00Z",
    "endTime": "2024-09-20T12:30:00Z",
    "description": "An introductory quiz on the fundamentals of machine learning.",
    "location": "Online",
    "batch": "11th"
  },
  {
    "id": "quiz4",
    "title": "Web Development with React",
    "date": "2024-09-25",
    "startTime": "2024-09-25T13:00:00Z",
    "endTime": "2024-09-25T14:30:00Z",
    "description": "A comprehensive quiz on React.js and modern web development practices.",
    "location": "Lab 101",
    "batch": "11th"
  },
  {
    "id": "quiz5",
    "title": "Data Structures and Algorithms",
    "date": "2024-09-30",
    "startTime": "2024-09-30T10:00:00Z",
    "endTime": "2024-09-30T11:30:00Z",
    "description": "A challenging quiz focused on data structures and algorithms.",
    "location": "Room 301",
    "batch": "12th"
  },
  {
    "id": "quiz6",
    "title": "Artificial Intelligence Basics",
    "date": "2024-10-05",
    "startTime": "2024-10-05T09:00:00Z",
    "endTime": "2024-10-05T10:30:00Z",
    "description": "An introductory quiz on the basics of artificial intelligence.",
    "location": "Online",
    "batch": "10th"
  }
]
